recordmymeeting/__init__.py
recordmymeeting/cli.py
recordmymeeting/core.py
recordmymeeting/device_manager.py
recordmymeeting/gui_app.py
recordmymeeting/utils.py
recordmymeeting-0.2.0.dist-info/METADATA
recordmymeeting-0.2.0.dist-info/WHEEL
recordmymeeting-0.2.0.dist-info/entry_points.txt
recordmymeeting-0.2.0.dist-info/top_level.txt
recordmymeeting-0.2.0.dist-info/RECORD
