Metadata-Version: 2.4
Name: recordmymeeting
Version: 0.2.0
Summary: Effortlessly capture audio and screen with intelligent device detection
Home-page: https://github.com/sachincse/recordmymeeting
Author: Sachin Singh
Author-email: sachincs95@gmail.com
Project-URL: Bug Tracker, https://github.com/sachincse/recordmymeeting/issues
Project-URL: Documentation, https://github.com/sachincse/recordmymeeting#readme
Project-URL: Source Code, https://github.com/sachincse/recordmymeeting
Classifier: Programming Language :: Python :: 3
Classifier: Programming Language :: Python :: 3 :: Only
Classifier: Operating System :: OS Independent
Classifier: Topic :: Multimedia :: Sound/Audio :: Capture/Recording
Classifier: Topic :: Multimedia :: Video :: Capture
Requires-Python: >=3.8
Requires-Dist: pyaudio>=0.2.11
Requires-Dist: opencv-python>=4.8.0
Requires-Dist: numpy>=1.19.0
Requires-Dist: mss>=6.1.0
Dynamic: author
Dynamic: author-email
Dynamic: classifier
Dynamic: description
Dynamic: description-content-type
Dynamic: home-page
Dynamic: project-url
Dynamic: requires-dist
Dynamic: requires-python
Dynamic: summary
